pathify/__init__.py
pathify/application.py
pathifyapi-0.0.2b0.dist-info/METADATA
pathifyapi-0.0.2b0.dist-info/WHEEL
pathifyapi-0.0.2b0.dist-info/RECORD
