Metadata-Version: 2.1
Name: PathifyAPI
Version: 0.0.2b0
Summary: FastAPI based library for create API.
License: GNU
Author: Ivan Kriventsev
Author-email: dirtyhornet277@gmail.com
Requires-Python: >=3.12,<4.0
Classifier: License :: Other/Proprietary License
Classifier: Programming Language :: Python :: 3
Classifier: Programming Language :: Python :: 3.12
Classifier: Programming Language :: Python :: 3.13
Requires-Dist: fastapi (>=0.115.5,<0.116.0)
